{
  "timestamp": "2026-06-25T05:26:08.892Z",
  "state_hash": "sha256:42c60e3a91b352cedbca2eefc5f7695741e63f4471105bd2a1ccad247090a669",
  "commit": "d8a8384",
  "system_state": {
    "phase": "Decision Execution System",
    "intelligence_level": "Level 3 - Decision Support",
    "loop_status": {
      "signal": true,
      "reasoning": true,
      "decision": true,
      "simulation": true,
      "execution": false,
      "feedback": false
    },
    "weakest_stage": "execution"
  },
  "architecture_layers": {
    "universal_intelligence_engine": "live",
    "domain_execution_systems": "live",
    "ai_decision_layer": "live",
    "execution_fabric": "partial",
    "ai_workforce": "live",
    "connectors": "live",
    "execution_outcome_binding": "modeled"
  },
  "recent_changes": [
    "Add Launch KPI dashboard tab (Intelligence & Analytics)",
    "Adopt SECC OS design tokens in Command Suite",
    "Redesign landing page platform-first (SECC OS) + design tokens"
  ],
  "active_focus": {
    "primary_workstream": "Property Execution Fabric",
    "blocked_expansion": [
      "No new domains",
      "No new agent types"
    ]
  },
  "risk_state": {
    "primary_risk": "Execution fragmentation",
    "secondary_risk": "Over-expansion of domain system",
    "stability": "moderate"
  },
  "next_required_action": "Build Property Execution Fabric (n8n + Yardi + CRM IQ integration)"
}
